MANIFEST.in
NEWS.txt
README.rst
setup.py
src/snurtle/__init__.py
src/snurtle/cmd.py
src/snurtle/cmd2.py
src/snurtle/config.py
src/snurtle/jsonrpc.py
src/snurtle/rpcclient.py
src/snurtle/shell.py
src/snurtle/snurtle
src/snurtle/version.py
src/snurtle.egg-info/PKG-INFO
src/snurtle.egg-info/SOURCES.txt
src/snurtle.egg-info/dependency_links.txt
src/snurtle.egg-info/not-zip-safe
src/snurtle.egg-info/requires.txt
src/snurtle.egg-info/top_level.txt
src/snurtle/bundles/__init__.py
src/snurtle/bundles/clibundle.py
src/snurtle/bundles/collection.py
src/snurtle/bundles/common.py
src/snurtle/bundles/contact.py
src/snurtle/bundles/enterprise.py
src/snurtle/bundles/process.py
src/snurtle/bundles/project.py
src/snurtle/bundles/route.py
src/snurtle/bundles/task.py
src/snurtle/bundles/team.py