Metadata-Version: 1.1
Name: snurtle
Version: 0.99.4
Summary: CLI for the OpenGroupware Collaboration/Workflow Platform
Home-page: http://sourceforge.net/p/snurtle/home/Home/
Author: Adam Tauno Williams
Author-email: awilliam@opengroupware.us
License: MIT
Keywords: workflow webdav bpml caldav icalendar scheduling todo
Platform: UNKNOWN
Classifier: Development Status :: 4 - Beta
Classifier: Intended Audience :: Information Technology
Classifier: License :: OSI Approved :: MIT License
Classifier: Programming Language :: Python :: 2.6
Classifier: Topic :: Office/Business :: Scheduling
Classifier: Topic :: Office/Business :: Groupware
